{"platform":"ASOMATE-ESP","data":[{"name":"av-scene","odatype":"avanzadas","active":true,"minimize":true,"binds":{},"attr":{"class":"","v-bind:automatic-scene":true,"end-audio":"","v-bind:force-oks":0},"content":[{"name":"av-start","odatype":"avanzadas","active":true,"minimize":false,"binds":{},"attr":{},"content":[],"id":"ComenzarODA","location":"0,0"}],"id":"Comenzar","location":"0"},{"name":"av-scene","odatype":"avanzadas","active":true,"minimize":true,"binds":{},"attr":{"class":"","v-bind:automatic-scene":true,"end-audio":"","v-bind:force-oks":"2"},"content":[{"name":"av-info","odatype":"avanzadas","active":true,"minimize":false,"binds":{},"attr":{"title":"Una sana receta","interaction":"drag","class":""},"content":[{"name":"action-timeline","odatype":"avanzadas","active":true,"minimize":false,"binds":{},"attr":{"show":"","hide":"1","completed":"1","completed-audio":"","ok":"","ok-audio":"","error":"","error-audio":""},"content":[{"name":"module-audiotext","active":true,"minimize":false,"odatype":"avanzadas","binds":{},"attr":{"text":"Hoy prepararemos un postre delicioso: ¡Paletas heladas de plátano!                                                ","audio":"https://ucarecdn.com/26eaf9e6-9f55-405a-87db-25e926a5a33b/","v-bind:autoplay":true,"class":""},"content":[],"id":"075116045","location":"1,0,0,0"}],"id":"intro","location":"1,0,0"},{"name":"action-timeline","odatype":"avanzadas","active":true,"minimize":false,"binds":{},"attr":{"show":"1","hide":"2","completed":"2","completed-audio":"","ok":"","ok-audio":"","error":"","error-audio":""},"content":[{"name":"module-audiotext","active":true,"minimize":false,"odatype":"avanzadas","binds":{},"attr":{"text":"¿Qué necesitamos?","audio":"https://ucarecdn.com/4ab82894-fb0d-4278-bcc2-f67c558b3537/","v-bind:autoplay":true,"class":""},"content":[],"id":"00bb2ceb2","location":"1,0,1,0"}],"id":"¿Qué necesitamos?","location":"1,0,1"},{"name":"action-timeline","odatype":"avanzadas","active":true,"minimize":false,"binds":{},"attr":{"show":"2","hide":"3","completed":"3","completed-audio":"","ok":"","ok-audio":"","error":"","error-audio":""},"content":[{"name":"module-audiotext","active":true,"minimize":false,"odatype":"avanzadas","binds":{},"attr":{"text":"","audio":"https://ucarecdn.com/66cb4c28-df08-4908-be58-71d1e5465149/","v-bind:autoplay":true,"class":""},"content":[],"id":"00bb2ceb2","location":"1,0,2,0"}],"id":"Ingredientes:","location":"1,0,2"},{"name":"action-timeline","odatype":"avanzadas","active":true,"minimize":false,"binds":{},"attr":{"show":"3","hide":"4","completed":"4","completed-audio":"","ok":"","ok-audio":"","error":"","error-audio":""},"content":[{"name":"module-audiotext","active":true,"minimize":false,"odatype":"avanzadas","binds":{},"attr":{"text":"Ingredientes: 4 palitos de madera. 2 plátanos grandes partidos por la mitad. Nuez picada. 2 cucharadas de crema de cacahuate. 2 cucharadas de crema de avellanas. Coco rallado. Chispas de chocolate / chispas de colores.","audio":"https://ucarecdn.com/115f8f69-70c8-4975-bcce-31186a32839d/","v-bind:autoplay":true,"class":""},"content":[],"id":"00bb2ceb2","location":"1,0,3,0"}],"id":"ingredientes: todos","location":"1,0,3"},{"name":"action-timeline","odatype":"avanzadas","active":true,"minimize":false,"binds":{},"attr":{"show":"4","hide":"5","completed":"5","completed-audio":"","ok":"","ok-audio":"","error":"","error-audio":""},"content":[{"name":"module-audiotext","active":true,"minimize":false,"odatype":"avanzadas","binds":{},"attr":{"text":"¿Cómo lo vamos a lograr?","audio":"https://ucarecdn.com/fe869d21-3989-4c09-856d-0d433369928f/","v-bind:autoplay":true,"class":""},"content":[],"id":"00bb2ceb2","location":"1,0,4,0"}],"id":"¿Cómo lo vamos a lograr?","location":"1,0,4"},{"name":"action-timeline","odatype":"avanzadas","active":true,"minimize":false,"binds":{},"attr":{"show":"5","hide":"","completed":"6","completed-audio":"","ok":"","ok-audio":"","error":"","error-audio":""},"content":[{"name":"module-audiotext","active":true,"minimize":false,"odatype":"avanzadas","binds":{},"attr":{"text":"Con ayuda de un adulto inserta la mitad del plátano en el palito de madera.","audio":"https://ucarecdn.com/d2ea3f45-74f8-42d1-95d6-0e9cdc2268ac/","v-bind:autoplay":true,"class":""},"content":[],"id":"00bb2ceb2","location":"1,0,5,0"}],"id":"Platano","location":"1,0,5"}],"id":"LaterialInfo","location":"1,0"},{"name":"av-activity","odatype":"avanzadas","active":true,"minimize":false,"binds":{},"attr":{"class":""},"content":[{"name":"div","active":true,"minimize":false,"binds":{},"attr":{"class":" w-fit relative"},"content":[{"name":"layout-img","active":true,"minimize":false,"binds":{},"attr":{"v-bind:img-variable":null,"img":"https://ucarecdn.com/03e49b8b-df1f-4574-ab7b-44a2e74a28ce/","class":""},"content":[],"id":"0d93e8e4b","location":"1,1,0,0"},{"name":"action-timeline","odatype":"avanzadas","active":true,"minimize":false,"binds":{},"attr":{"show":"6","hide":"","completed":"","completed-audio":"","ok":"","ok-audio":"","error":"","error-audio":""},"content":[{"name":"div","active":true,"minimize":false,"binds":{},"attr":{"class":" is-overlapping-item absolute w-[52%] h-[29%] left-[42%] top-[61%]"},"content":[{"name":"module-drop","active":true,"minimize":false,"binds":{},"attr":{"name":"drop1","design":1,"answer":"a","limit":2,"class":" w-full h-full bg-pastel6","v-bind:no-arrow":false,"v-bind:horizontal":true},"content":[],"id":"02182ad5b","location":"1,1,0,1,0,0"}],"id":"Zona","location":"1,1,0,1,0"},{"name":"div","active":true,"minimize":false,"binds":{},"attr":{"class":" is-overlapping-item absolute w-[13%] h-[10%] left-[41%] top-[44%]"},"content":[{"name":"module-drag","active":true,"minimize":false,"binds":{},"attr":{"v-bind:only-ok":true,"v-bind:only-error":false,"v-bind:allok":false,"dropzone":"drop1","answer":"a","liner":0,"connector":0,"design":"","class":"",":inmediate":true},"content":[{"name":"layout-img","active":true,"minimize":false,"binds":{},"attr":{"v-bind:img-variable":null,"img":"https://ucarecdn.com/574d8e1c-de9a-4f06-8b2b-3599639d9ced/","class":""},"content":[],"id":"018909f9b","location":"1,1,0,1,1,0,0"}],"id":"0515e8516","location":"1,1,0,1,1,0"}],"id":"Platano","location":"1,1,0,1,1"},{"name":"div","active":true,"minimize":false,"binds":{},"attr":{"class":" is-overlapping-item absolute w-[15%] h-[2%] left-[68%] top-[51%]"},"content":[{"name":"module-drag","active":true,"minimize":false,"binds":{},"attr":{"v-bind:only-ok":true,"v-bind:only-error":false,"v-bind:allok":false,"dropzone":"drop1","answer":"a","liner":0,"connector":0,"design":"","class":"",":inmediate":true},"content":[{"name":"layout-img","active":true,"minimize":false,"binds":{},"attr":{"v-bind:img-variable":null,"img":"https://ucarecdn.com/f1df4b48-aaba-457d-9979-42f99580efd5/","class":""},"content":[],"id":"08e2b07a3","location":"1,1,0,1,2,0,0"}],"id":"0e273a474","location":"1,1,0,1,2,0"}],"id":"palito","location":"1,1,0,1,2"}],"id":"Respuestas","location":"1,1,0,1"},{"name":"div","active":true,"minimize":false,"binds":{},"attr":{"class":" is-overlapping-item absolute w-[10%] h-[10%] left-[15%] top-[36%]"},"content":[{"name":"layout-img","active":true,"minimize":false,"binds":{},"attr":{"v-bind:img-variable":null,"img":"https://ucarecdn.com/a9dbbfb0-3b63-4814-b93c-5f5840f79282/","class":""},"content":[],"id":"0065be52a","location":"1,1,0,2,0"}],"id":"Avellana","location":"1,1,0,2"},{"name":"div","active":true,"minimize":false,"binds":{},"attr":{"class":" is-overlapping-item absolute w-[10%] h-[10%] left-[29%] top-[37%]"},"content":[{"name":"layout-img","active":true,"minimize":false,"binds":{},"attr":{"v-bind:img-variable":null,"img":"https://ucarecdn.com/0afd09ab-99a4-4193-85eb-0a185e12d757/","class":""},"content":[],"id":"00399638b","location":"1,1,0,3,0"}],"id":"cacahuate","location":"1,1,0,3"},{"name":"div","active":true,"minimize":false,"binds":{},"attr":{"class":" is-overlapping-item absolute w-[10%] h-[5%] left-[88%] top-[51%]"},"content":[{"name":"layout-img","active":true,"minimize":false,"binds":{},"attr":{"v-bind:img-variable":null,"img":"https://ucarecdn.com/9b30593d-2c28-4726-a6a2-5435492f4f94/","class":""},"content":[],"id":"066585ef1","location":"1,1,0,4,0"}],"id":"nuez","location":"1,1,0,4"},{"name":"div","active":true,"minimize":false,"binds":{},"attr":{"class":" is-overlapping-item absolute w-[10%] h-[10%] left-[3%] top-[30%]"},"content":[{"name":"layout-img","active":true,"minimize":false,"binds":{},"attr":{"v-bind:img-variable":null,"img":"https://ucarecdn.com/4bd770bf-0af1-4a3b-b0e9-4b147e33b442/","class":""},"content":[],"id":"055de1580","location":"1,1,0,5,0"}],"id":"coco","location":"1,1,0,5"},{"name":"div","active":true,"minimize":false,"binds":{},"attr":{"class":" is-overlapping-item absolute w-[10%] h-[7%] left-[57%] top-[49%]"},"content":[{"name":"layout-img","active":true,"minimize":false,"binds":{},"attr":{"v-bind:img-variable":null,"img":"https://ucarecdn.com/a4441cc5-f541-4f36-91b4-1ed01abcac02/","class":""},"content":[],"id":"0fecd7d41","location":"1,1,0,6,0"}],"id":"choco","location":"1,1,0,6"},{"name":"div","active":true,"minimize":false,"binds":{},"attr":{"class":" is-overlapping-item absolute w-[8%] h-[4%] left-[82%] top-[45%]"},"content":[{"name":"layout-img","active":true,"minimize":false,"binds":{},"attr":{"v-bind:img-variable":null,"img":"https://ucarecdn.com/962b0f43-913f-445c-872d-5f5b5703ed02/","class":""},"content":[],"id":"05e3e5bf4","location":"1,1,0,7,0"}],"id":"colores","location":"1,1,0,7"},{"name":"action-timeline","odatype":"avanzadas","active":true,"minimize":false,"binds":{},"attr":{"show":"3","hide":"","completed":"","completed-audio":"","ok":"","ok-audio":"","error":"","error-audio":""},"content":[{"name":"div","active":true,"minimize":false,"binds":{},"attr":{"class":" is-overlapping-item absolute w-[28%] h-[37%] left-[5%] top-[60%]"},"content":[{"name":"layout-img","active":true,"minimize":false,"binds":{},"attr":{"v-bind:img-variable":null,"img":"https://ucarecdn.com/3975eefa-c51a-4a0e-9697-5345d265572e/","class":""},"content":[],"id":"09d9ab7f1","location":"1,1,0,8,0,0"}],"id":"07659147b","location":"1,1,0,8,0"}],"id":"Receta","location":"1,1,0,8"}],"id":"002366884","location":"1,1,0"},{"name":"action-timeline","odatype":"avanzadas","active":true,"minimize":false,"binds":{},"attr":{"show":"6","hide":"","completed":"","completed-audio":"","ok":"","ok-audio":"","error":"","error-audio":""},"content":[],"id":"13288bdaa","location":"1,1,1"}],"id":"Actividad","location":"1,1"}],"id":"cocina","location":"1"},{"name":"av-scene","odatype":"avanzadas","active":true,"minimize":true,"binds":{},"attr":{"class":"","v-bind:automatic-scene":true,"end-audio":"","v-bind:force-oks":"2"},"content":[{"name":"av-info","odatype":"avanzadas","active":true,"minimize":false,"binds":{},"attr":{"title":"Una sana receta","interaction":"drag","class":""},"content":[{"name":"action-timeline","odatype":"avanzadas","active":true,"minimize":false,"binds":{},"attr":{"show":"","hide":"","completed":"1","completed-audio":"","ok":"","ok-audio":"","error":"","error-audio":""},"content":[{"name":"module-audiotext","active":true,"minimize":false,"odatype":"avanzadas","binds":{},"attr":{"text":"Cubre el plátano con crema de avellana, crema de cacahuate o ambas.","audio":"https://ucarecdn.com/5a19725f-c71a-4d65-8538-6582a4605265/","v-bind:autoplay":true,"class":""},"content":[],"id":"075116045","location":"2,0,0,0"}],"id":"paso 2","location":"2,0,0"}],"id":"LaterialInfo","location":"2,0"},{"name":"av-activity","odatype":"avanzadas","active":true,"minimize":false,"binds":{},"attr":{"class":""},"content":[{"name":"div","active":true,"minimize":false,"binds":{},"attr":{"class":" w-fit relative"},"content":[{"name":"layout-img","active":true,"minimize":false,"binds":{},"attr":{"v-bind:img-variable":null,"img":"https://ucarecdn.com/03e49b8b-df1f-4574-ab7b-44a2e74a28ce/","class":""},"content":[],"id":"0d93e8e4b","location":"2,1,0,0"},{"name":"div","active":true,"minimize":false,"binds":{},"attr":{"class":" is-overlapping-item absolute w-[15%] h-[2%] left-[59%] top-[76%]"},"content":[{"name":"layout-img","active":true,"minimize":false,"binds":{},"attr":{"v-bind:img-variable":null,"img":"https://ucarecdn.com/f1df4b48-aaba-457d-9979-42f99580efd5/","class":""},"content":[],"id":"0c4158add","location":"2,1,0,1,0"}],"id":"palito","location":"2,1,0,1"},{"name":"div","active":true,"minimize":false,"binds":{},"attr":{"class":" is-overlapping-item absolute w-[13%] h-[10%] left-[53%] top-[70%]"},"content":[{"name":"layout-img","active":true,"minimize":false,"binds":{},"attr":{"v-bind:img-variable":null,"img":"https://ucarecdn.com/574d8e1c-de9a-4f06-8b2b-3599639d9ced/","class":""},"content":[],"id":"0b2f7173e","location":"2,1,0,2,0"}],"id":"Platano","location":"2,1,0,2"},{"name":"action-timeline","odatype":"avanzadas","active":true,"minimize":false,"binds":{},"attr":{"show":"1","hide":"","completed":"","completed-audio":"","ok":"","ok-audio":"","error":"","error-audio":""},"content":[{"name":"div","active":true,"minimize":false,"binds":{},"attr":{"class":" is-overlapping-item absolute w-[13%] h-[12%] left-[53%] top-[69%]"},"content":[{"name":"module-drop","active":true,"minimize":false,"binds":{},"attr":{"name":"drop1","design":0,"answer":"a","limit":0,"class":" w-full h-full","v-bind:no-arrow":false,"v-bind:horizontal":false},"content":[],"id":"02182ad5b","location":"2,1,0,3,0,0"}],"id":"Zona","location":"2,1,0,3,0"},{"name":"div","active":true,"minimize":false,"binds":{},"attr":{"class":" is-overlapping-item absolute w-[10%] h-[10%] left-[15%] top-[36%]"},"content":[{"name":"module-drag","active":true,"minimize":false,"binds":{},"attr":{"v-bind:only-ok":false,"v-bind:only-error":false,"v-bind:allok":false,"dropzone":"drop1","answer":"a","liner":0,"connector":0,"design":"","class":"",":inmediate":true},"content":[{"name":"layout-img","active":true,"minimize":false,"binds":{},"attr":{"v-bind:img-variable":null,"img":"https://ucarecdn.com/a9dbbfb0-3b63-4814-b93c-5f5840f79282/","class":""},"content":[],"id":"018909f9b","location":"2,1,0,3,1,0,0"}],"id":"0515e8516","location":"2,1,0,3,1,0"}],"id":"Avellana","location":"2,1,0,3,1"},{"name":"div","active":true,"minimize":false,"binds":{},"attr":{"class":" is-overlapping-item absolute w-[10%] h-[10%] left-[29%] top-[37%]"},"content":[{"name":"module-drag","active":true,"minimize":false,"binds":{},"attr":{"v-bind:only-ok":false,"v-bind:only-error":false,"v-bind:allok":false,"dropzone":"drop1","answer":"a","liner":0,"connector":0,"design":"","class":"",":inmediate":true},"content":[{"name":"layout-img","active":true,"minimize":false,"binds":{},"attr":{"v-bind:img-variable":null,"img":"https://ucarecdn.com/0afd09ab-99a4-4193-85eb-0a185e12d757/","class":""},"content":[],"id":"018909f9b","location":"2,1,0,3,2,0,0"}],"id":"0515e8516","location":"2,1,0,3,2,0"}],"id":"cacahuate","location":"2,1,0,3,2"}],"id":"Respuestas","location":"2,1,0,3"},{"name":"div","active":true,"minimize":false,"binds":{},"attr":{"class":" is-overlapping-item absolute w-[10%] h-[5%] left-[88%] top-[51%]"},"content":[{"name":"layout-img","active":true,"minimize":false,"binds":{},"attr":{"v-bind:img-variable":null,"img":"https://ucarecdn.com/9b30593d-2c28-4726-a6a2-5435492f4f94/","class":""},"content":[],"id":"0c16429d1","location":"2,1,0,4,0"}],"id":"nuez","location":"2,1,0,4"},{"name":"div","active":true,"minimize":false,"binds":{},"attr":{"class":" is-overlapping-item absolute w-[10%] h-[10%] left-[3%] top-[30%]"},"content":[{"name":"layout-img","active":true,"minimize":false,"binds":{},"attr":{"v-bind:img-variable":null,"img":"https://ucarecdn.com/4bd770bf-0af1-4a3b-b0e9-4b147e33b442/","class":""},"content":[],"id":"0239f7f87","location":"2,1,0,5,0"}],"id":"coco","location":"2,1,0,5"},{"name":"div","active":true,"minimize":false,"binds":{},"attr":{"class":" is-overlapping-item absolute w-[10%] h-[7%] left-[57%] top-[49%]"},"content":[{"name":"layout-img","active":true,"minimize":false,"binds":{},"attr":{"v-bind:img-variable":null,"img":"https://ucarecdn.com/a4441cc5-f541-4f36-91b4-1ed01abcac02/","class":""},"content":[],"id":"0fa6e8f31","location":"2,1,0,6,0"}],"id":"choco","location":"2,1,0,6"},{"name":"div","active":true,"minimize":false,"binds":{},"attr":{"class":" is-overlapping-item absolute w-[8%] h-[4%] left-[82%] top-[45%]"},"content":[{"name":"layout-img","active":true,"minimize":false,"binds":{},"attr":{"v-bind:img-variable":null,"img":"https://ucarecdn.com/962b0f43-913f-445c-872d-5f5b5703ed02/","class":""},"content":[],"id":"0d22ef400","location":"2,1,0,7,0"}],"id":"colores","location":"2,1,0,7"},{"name":"action-timeline","odatype":"avanzadas","active":true,"minimize":false,"binds":{},"attr":{"show":"","hide":"","completed":"","completed-audio":"","ok":"","ok-audio":"","error":"","error-audio":""},"content":[{"name":"div","active":true,"minimize":false,"binds":{},"attr":{"class":" is-overlapping-item absolute w-[28%] h-[37%] left-[5%] top-[60%]"},"content":[{"name":"layout-img","active":true,"minimize":false,"binds":{},"attr":{"v-bind:img-variable":null,"img":"https://ucarecdn.com/3975eefa-c51a-4a0e-9697-5345d265572e/","class":""},"content":[],"id":"09d9ab7f1","location":"2,1,0,8,0,0"}],"id":"07659147b","location":"2,1,0,8,0"}],"id":"Receta","location":"2,1,0,8"}],"id":"002366884","location":"2,1,0"}],"id":"Actividad","location":"2,1"}],"id":"2","location":"2"},{"name":"av-scene","odatype":"avanzadas","active":true,"minimize":true,"binds":{},"attr":{"class":"","v-bind:automatic-scene":true,"end-audio":"","v-bind:force-oks":"4"},"content":[{"name":"av-info","odatype":"avanzadas","active":true,"minimize":false,"binds":{},"attr":{"title":"Una sana receta","interaction":"drag","class":""},"content":[{"name":"action-timeline","odatype":"avanzadas","active":true,"minimize":false,"binds":{},"attr":{"show":"","hide":"","completed":"1","completed-audio":"","ok":"","ok-audio":"","error":"","error-audio":""},"content":[{"name":"module-audiotext","active":true,"minimize":false,"odatype":"avanzadas","binds":{},"attr":{"text":"Espolvorea la nuez picada, las chispas de chocolate, el coco rayado o la combinación que tú desees sobre el plátano.","audio":"https://ucarecdn.com/6173ad2d-ad07-4b84-b8f6-a78f56b7b1b0/","v-bind:autoplay":true,"class":""},"content":[],"id":"075116045","location":"3,0,0,0"}],"id":"paso 2","location":"3,0,0"}],"id":"LaterialInfo","location":"3,0"},{"name":"av-activity","odatype":"avanzadas","active":true,"minimize":false,"binds":{},"attr":{"class":""},"content":[{"name":"div","active":true,"minimize":false,"binds":{},"attr":{"class":" w-fit relative"},"content":[{"name":"layout-img","active":true,"minimize":false,"binds":{},"attr":{"v-bind:img-variable":null,"img":"https://ucarecdn.com/03e49b8b-df1f-4574-ab7b-44a2e74a28ce/","class":""},"content":[],"id":"Respuestas 3🟨","location":"3,1,0,0"},{"name":"action-timeline","odatype":"avanzadas","active":true,"minimize":true,"binds":{},"attr":{"show":"1","hide":"","completed":"","completed-audio":"","ok":"","ok-audio":"","error":"","error-audio":""},"content":[{"name":"div","active":true,"minimize":true,"binds":{},"attr":{"class":" is-overlapping-item absolute w-[10%] h-[15%] left-[55%] top-[61%]"},"content":[{"name":"module-drop","active":true,"minimize":false,"binds":{},"attr":{"name":"drop1","design":0,"answer":"a","limit":0,"class":" w-full h-full","v-bind:no-arrow":false,"v-bind:horizontal":false},"content":[],"id":"02182ad5b","location":"3,1,0,1,0,0"}],"id":"Zona1","location":"3,1,0,1,0"},{"name":"div","active":true,"minimize":false,"binds":{},"attr":{"class":" is-overlapping-item absolute w-[10%] h-[5%] left-[88%] top-[51%]"},"content":[{"name":"module-drag","active":true,"minimize":false,"binds":{},"attr":{"v-bind:only-ok":false,"v-bind:only-error":false,"v-bind:allok":false,"dropzone":"drop1","answer":"a","liner":0,"connector":0,"design":"","class":"",":inmediate":true},"content":[{"name":"layout-img","active":true,"minimize":false,"binds":{},"attr":{"v-bind:img-variable":null,"img":"https://ucarecdn.com/9b30593d-2c28-4726-a6a2-5435492f4f94/","class":""},"content":[],"id":"018909f9b","location":"3,1,0,1,1,0,0"}],"id":"0515e8516","location":"3,1,0,1,1,0"}],"id":"nuez","location":"3,1,0,1,1"},{"name":"div","active":true,"minimize":false,"binds":{},"attr":{"class":" is-overlapping-item absolute w-[10%] h-[10%] left-[3%] top-[30%]"},"content":[{"name":"module-drag","active":true,"minimize":false,"binds":{},"attr":{"v-bind:only-ok":false,"v-bind:only-error":false,"v-bind:allok":false,"dropzone":"drop1","answer":"a","liner":0,"connector":0,"design":"","class":"",":inmediate":true},"content":[{"name":"layout-img","active":true,"minimize":false,"binds":{},"attr":{"v-bind:img-variable":null,"img":"https://ucarecdn.com/4bd770bf-0af1-4a3b-b0e9-4b147e33b442/","class":""},"content":[],"id":"018909f9b","location":"3,1,0,1,2,0,0"}],"id":"0515e8516","location":"3,1,0,1,2,0"}],"id":"coco","location":"3,1,0,1,2"},{"name":"div","active":true,"minimize":false,"binds":{},"attr":{"class":" is-overlapping-item absolute w-[10%] h-[7%] left-[57%] top-[49%]"},"content":[{"name":"module-drag","active":true,"minimize":false,"binds":{},"attr":{"v-bind:only-ok":false,"v-bind:only-error":false,"v-bind:allok":false,"dropzone":"drop1","answer":"a","liner":0,"connector":0,"design":"","class":"",":inmediate":true},"content":[{"name":"layout-img","active":true,"minimize":false,"binds":{},"attr":{"v-bind:img-variable":null,"img":"https://ucarecdn.com/a4441cc5-f541-4f36-91b4-1ed01abcac02/","class":""},"content":[],"id":"018909f9b","location":"3,1,0,1,3,0,0"}],"id":"0515e8516","location":"3,1,0,1,3,0"}],"id":"choco","location":"3,1,0,1,3"},{"name":"div","active":true,"minimize":false,"binds":{},"attr":{"class":" is-overlapping-item absolute w-[8%] h-[4%] left-[82%] top-[45%]"},"content":[{"name":"module-drag","active":true,"minimize":false,"binds":{},"attr":{"v-bind:only-ok":false,"v-bind:only-error":false,"v-bind:allok":false,"dropzone":"drop1","answer":"a","liner":0,"connector":0,"design":"","class":"",":inmediate":true},"content":[{"name":"layout-img","active":true,"minimize":false,"binds":{},"attr":{"v-bind:img-variable":null,"img":"https://ucarecdn.com/962b0f43-913f-445c-872d-5f5b5703ed02/","class":""},"content":[],"id":"018909f9b","location":"3,1,0,1,4,0,0"}],"id":"0515e8516","location":"3,1,0,1,4,0"}],"id":"colores","location":"3,1,0,1,4"}],"id":"6e9d58357","location":"3,1,0,1"},{"name":"div","active":true,"minimize":false,"binds":{},"attr":{"class":" is-overlapping-item absolute w-[15%] h-[2%] left-[59%] top-[76%]"},"content":[{"name":"layout-img","active":true,"minimize":false,"binds":{},"attr":{"v-bind:img-variable":null,"img":"https://ucarecdn.com/f1df4b48-aaba-457d-9979-42f99580efd5/","class":""},"content":[],"id":"0c4158add","location":"3,1,0,2,0"}],"id":"palito","location":"3,1,0,2"},{"name":"div","active":true,"minimize":false,"binds":{},"attr":{"class":" is-overlapping-item absolute w-[13%] h-[10%] left-[53%] top-[70%]"},"content":[{"name":"layout-img","active":true,"minimize":false,"binds":{},"attr":{"v-bind:img-variable":null,"img":"https://ucarecdn.com/574d8e1c-de9a-4f06-8b2b-3599639d9ced/","class":""},"content":[],"id":"0b2f7173e","location":"3,1,0,3,0"}],"id":"Platano","location":"3,1,0,3"},{"name":"div","active":true,"minimize":false,"binds":{},"attr":{"class":" is-overlapping-item absolute w-[12%] h-[10%] left-[54%] top-[70%]"},"content":[{"name":"layout-img","active":true,"minimize":false,"binds":{},"attr":{"v-bind:img-variable":null,"img":"https://ucarecdn.com/a9dbbfb0-3b63-4814-b93c-5f5840f79282/","class":""},"content":[],"id":"0e4b50ddb","location":"3,1,0,4,0"}],"id":"Avellana","location":"3,1,0,4"},{"name":"action-timeline","odatype":"avanzadas","active":true,"minimize":false,"binds":{},"attr":{"show":"","hide":"","completed":"","completed-audio":"","ok":"","ok-audio":"","error":"","error-audio":""},"content":[{"name":"div","active":true,"minimize":false,"binds":{},"attr":{"class":" is-overlapping-item absolute w-[28%] h-[37%] left-[5%] top-[60%]"},"content":[{"name":"layout-img","active":true,"minimize":false,"binds":{},"attr":{"v-bind:img-variable":null,"img":"https://ucarecdn.com/3975eefa-c51a-4a0e-9697-5345d265572e/","class":""},"content":[],"id":"09d9ab7f1","location":"3,1,0,5,0,0"}],"id":"07659147b","location":"3,1,0,5,0"}],"id":"Receta","location":"3,1,0,5"},{"name":"div","active":true,"minimize":false,"binds":{},"attr":{"class":" is-overlapping-item absolute w-[12%] h-[10%] left-[54%] top-[69%]"},"content":[{"name":"layout-img","active":true,"minimize":false,"binds":{},"attr":{"v-bind:img-variable":null,"img":"https://ucarecdn.com/0afd09ab-99a4-4193-85eb-0a185e12d757/","class":""},"content":[],"id":"03a179d5a","location":"3,1,0,6,0"}],"id":"cacahuate","location":"3,1,0,6"}],"id":"002366884","location":"3,1,0"}],"id":"Actividad","location":"3,1"}],"id":"3","location":"3"},{"name":"av-scene","odatype":"avanzadas","active":true,"minimize":true,"binds":{},"attr":{"class":"","v-bind:automatic-scene":false,"end-audio":"","v-bind:force-oks":"2"},"content":[{"name":"av-info","odatype":"avanzadas","active":true,"minimize":false,"binds":{},"attr":{"title":"Una sana receta","interaction":"drag","class":""},"content":[{"name":"action-timeline","odatype":"avanzadas","active":true,"minimize":false,"binds":{},"attr":{"show":"","hide":"3","completed":"1","completed-audio":"","ok":"","ok-audio":"","error":"","error-audio":""},"content":[{"name":"module-audiotext","active":true,"minimize":false,"odatype":"avanzadas","binds":{},"attr":{"text":"Pon cada uno de los plátanos en un túper  y ¡Al congelador!","audio":"https://ucarecdn.com/0eaedeef-c565-47a5-a1c7-1571f4f42f1e/","v-bind:autoplay":true,"class":""},"content":[],"id":"075116045","location":"4,0,0,0"}],"id":"paso 2","location":"4,0,0"},{"name":"action-timeline","odatype":"avanzadas","active":true,"minimize":false,"binds":{},"attr":{"show":"3","hide":"4","completed":"4","completed-audio":"","ok":"","ok-audio":"","error":"","error-audio":""},"content":[{"name":"module-audiotext","active":true,"minimize":false,"odatype":"avanzadas","binds":{},"attr":{"text":"Espera de 2 a 3 horas a que se congele un poco el plátano.","audio":"https://ucarecdn.com/957d3513-6749-4e22-ac46-931dad807874/","v-bind:autoplay":true,"class":""},"content":[],"id":"075116045","location":"4,0,1,0"}],"id":"espera","location":"4,0,1"},{"name":"action-timeline","odatype":"avanzadas","active":true,"minimize":false,"binds":{},"attr":{"show":"4","hide":"5","completed":"5","completed-audio":"","ok":"","ok-audio":"","error":"","error-audio":""},"content":[{"name":"module-audiotext","active":true,"minimize":false,"odatype":"avanzadas","binds":{},"attr":{"text":"¡Disfruta!","audio":"https://ucarecdn.com/11974619-d82d-4891-a235-3451d5cabdc0/","v-bind:autoplay":true,"class":""},"content":[],"id":"075116045","location":"4,0,2,0"}],"id":"disfruta","location":"4,0,2"},{"name":"action-timeline","odatype":"avanzadas","active":true,"minimize":false,"binds":{},"attr":{"show":"5","hide":"6","completed":"6","completed-audio":"","ok":"","ok-audio":"","error":"","error-audio":""},"content":[{"name":"module-audiotext","active":true,"minimize":false,"odatype":"avanzadas","binds":{},"attr":{"text":"¡RECUERDA QUE PUEDES HACER LAS COMBINACIONES QUE TÚ QUIERAS!","audio":"https://ucarecdn.com/57a69eb8-9428-4697-9888-fb326a5a0bfb/","v-bind:autoplay":true,"class":""},"content":[],"id":"075116045","location":"4,0,3,0"}],"id":"🟥","location":"4,0,3"}],"id":"LaterialInfo","location":"4,0"},{"name":"av-activity","odatype":"avanzadas","active":true,"minimize":false,"binds":{},"attr":{"class":""},"content":[{"name":"div","active":true,"minimize":false,"binds":{},"attr":{"class":" w-fit relative"},"content":[{"name":"layout-img","active":true,"minimize":false,"binds":{},"attr":{"v-bind:img-variable":null,"img":"https://ucarecdn.com/03e49b8b-df1f-4574-ab7b-44a2e74a28ce/","class":""},"content":[],"id":"0d93e8e4b","location":"4,1,0,0"},{"name":"action-timeline","odatype":"avanzadas","active":true,"minimize":false,"binds":{},"attr":{"show":"1","hide":"2","completed":"","completed-audio":"","ok":"","ok-audio":"","error":"","error-audio":""},"content":[{"name":"div","active":true,"minimize":false,"binds":{},"attr":{"class":" is-overlapping-item absolute w-[25%] h-[20%] left-[69%] top-[66%]"},"content":[{"name":"layout-img","active":true,"minimize":false,"binds":{},"attr":{"v-bind:img-variable":null,"img":"https://ucarecdn.com/2c532a91-9ba1-49c1-a584-e61ba247acd6/","class":""},"content":[],"id":"01adbc20b","location":"4,1,0,1,0,0"}],"id":"bandeja","location":"4,1,0,1,0"},{"name":"div","active":true,"minimize":false,"binds":{},"attr":{"class":" is-overlapping-item absolute w-[25%] h-[11%] left-[69%] top-[63%]"},"content":[{"name":"module-drop","active":true,"minimize":false,"binds":{},"attr":{"name":"drop1","design":1,"answer":"a","limit":0,"class":" w-full h-full","v-bind:no-arrow":false,"v-bind:horizontal":false},"content":[],"id":"1f748ac55","location":"4,1,0,1,1,0"}],"id":"Zona1","location":"4,1,0,1,1"},{"name":"div","active":true,"minimize":false,"binds":{},"attr":{"class":" is-overlapping-item absolute w-[26%] h-[27%] left-[42%] top-[62%]"},"content":[{"name":"action-timeline","odatype":"avanzadas","active":true,"minimize":false,"binds":{},"attr":{"show":"","hide":"","completed":"","completed-audio":"","ok":"2","ok-audio":"","error":"","error-audio":""},"content":[{"name":"module-drag","active":true,"minimize":true,"binds":{},"attr":{"v-bind:only-ok":false,"v-bind:only-error":false,"v-bind:allok":false,"dropzone":"drop1","answer":"a","liner":0,"connector":0,"design":0,"class":" w-full h-full",":inmediate":true},"content":[{"name":"div","active":true,"minimize":false,"binds":{},"attr":{"class":" is-overlapping-item absolute w-[45%] h-[30%] left-[30%] top-[57%]"},"content":[{"name":"layout-img","active":true,"minimize":false,"binds":{},"attr":{"v-bind:img-variable":null,"img":"https://ucarecdn.com/f1df4b48-aaba-457d-9979-42f99580efd5/","class":""},"content":[],"id":"p","location":"4,1,0,1,2,0,0,0,0"}],"id":"palito","location":"4,1,0,1,2,0,0,0"},{"name":"div","active":true,"minimize":false,"binds":{},"attr":{"class":" is-overlapping-item absolute w-[45%] h-[30%] left-[10%] top-[34%]"},"content":[{"name":"layout-img","active":true,"minimize":false,"binds":{},"attr":{"v-bind:img-variable":null,"img":"https://ucarecdn.com/574d8e1c-de9a-4f06-8b2b-3599639d9ced/","class":""},"content":[],"id":"0b2f7173e","location":"4,1,0,1,2,0,0,1,0"}],"id":"Platano","location":"4,1,0,1,2,0,0,1"},{"name":"div","active":true,"minimize":false,"binds":{},"attr":{"class":" is-overlapping-item absolute w-[40%] h-[10%] left-[13%] top-[33%]"},"content":[{"name":"layout-img","active":true,"minimize":false,"binds":{},"attr":{"v-bind:img-variable":null,"img":"https://ucarecdn.com/a9dbbfb0-3b63-4814-b93c-5f5840f79282/","class":""},"content":[],"id":"0e4b50ddb","location":"4,1,0,1,2,0,0,2,0"}],"id":"Avellana","location":"4,1,0,1,2,0,0,2"},{"name":"div","active":true,"minimize":false,"binds":{},"attr":{"class":" is-overlapping-item absolute w-[35%] h-[10%] left-[15%] top-[30%]"},"content":[{"name":"layout-img","active":true,"minimize":false,"binds":{},"attr":{"v-bind:img-variable":null,"img":"https://ucarecdn.com/0afd09ab-99a4-4193-85eb-0a185e12d757/","class":""},"content":[],"id":"03a179d5a","location":"4,1,0,1,2,0,0,3,0"}],"id":"cacahuate","location":"4,1,0,1,2,0,0,3"},{"name":"div","active":true,"minimize":false,"binds":{},"attr":{"class":" is-overlapping-item absolute w-[30%] h-[5%] left-[13%] top-[33%]"},"content":[{"name":"layout-img","active":true,"minimize":false,"binds":{},"attr":{"v-bind:img-variable":null,"img":"https://ucarecdn.com/9b30593d-2c28-4726-a6a2-5435492f4f94/","class":""},"content":[],"id":"089763d88","location":"4,1,0,1,2,0,0,4,0"}],"id":"nuez","location":"4,1,0,1,2,0,0,4"},{"name":"div","active":true,"minimize":false,"binds":{},"attr":{"class":" is-overlapping-item absolute w-[30%] h-[10%] left-[17%] top-[20%]"},"content":[{"name":"layout-img","active":true,"minimize":false,"binds":{},"attr":{"v-bind:img-variable":null,"img":"https://ucarecdn.com/4bd770bf-0af1-4a3b-b0e9-4b147e33b442/","class":""},"content":[],"id":"0702063f1","location":"4,1,0,1,2,0,0,5,0"}],"id":"coco","location":"4,1,0,1,2,0,0,5"},{"name":"div","active":true,"minimize":false,"binds":{},"attr":{"class":" is-overlapping-item absolute w-[30%] h-[7%] left-[19%] top-[27%]"},"content":[{"name":"layout-img","active":true,"minimize":false,"binds":{},"attr":{"v-bind:img-variable":null,"img":"https://ucarecdn.com/a4441cc5-f541-4f36-91b4-1ed01abcac02/","class":""},"content":[],"id":"02a6a734d","location":"4,1,0,1,2,0,0,6,0"}],"id":"choco","location":"4,1,0,1,2,0,0,6"},{"name":"div","active":true,"minimize":false,"binds":{},"attr":{"class":" is-overlapping-item absolute w-[30%] h-[4%] left-[16%] top-[26%]"},"content":[{"name":"layout-img","active":true,"minimize":false,"binds":{},"attr":{"v-bind:img-variable":null,"img":"https://ucarecdn.com/962b0f43-913f-445c-872d-5f5b5703ed02/","class":""},"content":[],"id":"081a631d9","location":"4,1,0,1,2,0,0,7,0"}],"id":"colores","location":"4,1,0,1,2,0,0,7"}],"id":"🟪🟩","location":"4,1,0,1,2,0,0"}],"id":"0f4bc5c5f","location":"4,1,0,1,2,0"}],"id":"🟪","location":"4,1,0,1,2"}],"id":"Bandeja🟩","location":"4,1,0,1"},{"name":"action-timeline","odatype":"avanzadas","active":true,"minimize":false,"binds":{},"attr":{"show":"","hide":"","completed":"","completed-audio":"","ok":"","ok-audio":"","error":"","error-audio":""},"content":[{"name":"div","active":true,"minimize":false,"binds":{},"attr":{"class":" is-overlapping-item absolute w-[28%] h-[37%] left-[5%] top-[60%]"},"content":[{"name":"layout-img","active":true,"minimize":false,"binds":{},"attr":{"v-bind:img-variable":null,"img":"https://ucarecdn.com/3975eefa-c51a-4a0e-9697-5345d265572e/","class":""},"content":[],"id":"09d9ab7f1","location":"4,1,0,2,0,0"}],"id":"07659147b","location":"4,1,0,2,0"}],"id":"Receta","location":"4,1,0,2"},{"name":"action-timeline","odatype":"avanzadas","active":true,"minimize":false,"binds":{},"attr":{"show":"2","hide":"","completed":"","completed-audio":"","ok":"","ok-audio":"","error":"","error-audio":""},"content":[{"name":"div","active":true,"minimize":false,"binds":{},"attr":{"class":" is-overlapping-item absolute w-[31%] h-[29%] left-[64%] top-[5%]"},"content":[{"name":"module-drop","active":true,"minimize":false,"binds":{},"attr":{"name":"drop1","design":1,"answer":"a","limit":0,"class":" w-full h-full","v-bind:no-arrow":false,"v-bind:horizontal":false},"content":[],"id":"1f748ac55","location":"4,1,0,3,0,0"}],"id":"Zona1","location":"4,1,0,3,0"},{"name":"div","active":true,"minimize":false,"binds":{},"attr":{"class":" is-overlapping-item absolute w-[26%] h-[27%] left-[54%] top-[62%]"},"content":[{"name":"action-timeline","odatype":"avanzadas","active":true,"minimize":false,"binds":{},"attr":{"show":"","hide":"","completed":"","completed-audio":"","ok":"3","ok-audio":"","error":"","error-audio":""},"content":[{"name":"module-drag","active":true,"minimize":true,"binds":{},"attr":{"v-bind:only-ok":false,"v-bind:only-error":false,"v-bind:allok":false,"dropzone":"drop1","answer":"a","liner":0,"connector":0,"design":0,"class":" w-full h-full",":inmediate":true},"content":[{"name":"div","active":true,"minimize":false,"binds":{},"attr":{"class":" is-overlapping-item absolute w-[100%] h-[20%] left-[1%] top-[34%]"},"content":[{"name":"layout-img","active":true,"minimize":false,"binds":{},"attr":{"v-bind:img-variable":null,"img":"https://ucarecdn.com/2c532a91-9ba1-49c1-a584-e61ba247acd6/","class":""},"content":[],"id":"094b01326","location":"4,1,0,3,1,0,0,0,0"}],"id":"bandeja","location":"4,1,0,3,1,0,0,0"},{"name":"div","active":true,"minimize":false,"binds":{},"attr":{"class":" is-overlapping-item absolute w-[45%] h-[30%] left-[30%] top-[57%]"},"content":[{"name":"layout-img","active":true,"minimize":false,"binds":{},"attr":{"v-bind:img-variable":null,"img":"https://ucarecdn.com/f1df4b48-aaba-457d-9979-42f99580efd5/","class":""},"content":[],"id":"p","location":"4,1,0,3,1,0,0,1,0"}],"id":"palito","location":"4,1,0,3,1,0,0,1"},{"name":"div","active":true,"minimize":false,"binds":{},"attr":{"class":" is-overlapping-item absolute w-[45%] h-[30%] left-[10%] top-[34%]"},"content":[{"name":"layout-img","active":true,"minimize":false,"binds":{},"attr":{"v-bind:img-variable":null,"img":"https://ucarecdn.com/574d8e1c-de9a-4f06-8b2b-3599639d9ced/","class":""},"content":[],"id":"0b2f7173e","location":"4,1,0,3,1,0,0,2,0"}],"id":"Platano","location":"4,1,0,3,1,0,0,2"},{"name":"div","active":true,"minimize":false,"binds":{},"attr":{"class":" is-overlapping-item absolute w-[40%] h-[10%] left-[13%] top-[33%]"},"content":[{"name":"layout-img","active":true,"minimize":false,"binds":{},"attr":{"v-bind:img-variable":null,"img":"https://ucarecdn.com/a9dbbfb0-3b63-4814-b93c-5f5840f79282/","class":""},"content":[],"id":"0e4b50ddb","location":"4,1,0,3,1,0,0,3,0"}],"id":"Avellana","location":"4,1,0,3,1,0,0,3"},{"name":"div","active":true,"minimize":false,"binds":{},"attr":{"class":" is-overlapping-item absolute w-[35%] h-[10%] left-[15%] top-[30%]"},"content":[{"name":"layout-img","active":true,"minimize":false,"binds":{},"attr":{"v-bind:img-variable":null,"img":"https://ucarecdn.com/0afd09ab-99a4-4193-85eb-0a185e12d757/","class":""},"content":[],"id":"03a179d5a","location":"4,1,0,3,1,0,0,4,0"}],"id":"cacahuate","location":"4,1,0,3,1,0,0,4"},{"name":"div","active":true,"minimize":false,"binds":{},"attr":{"class":" is-overlapping-item absolute w-[30%] h-[5%] left-[13%] top-[33%]"},"content":[{"name":"layout-img","active":true,"minimize":false,"binds":{},"attr":{"v-bind:img-variable":null,"img":"https://ucarecdn.com/9b30593d-2c28-4726-a6a2-5435492f4f94/","class":""},"content":[],"id":"089763d88","location":"4,1,0,3,1,0,0,5,0"}],"id":"nuez","location":"4,1,0,3,1,0,0,5"},{"name":"div","active":true,"minimize":false,"binds":{},"attr":{"class":" is-overlapping-item absolute w-[30%] h-[10%] left-[17%] top-[20%]"},"content":[{"name":"layout-img","active":true,"minimize":false,"binds":{},"attr":{"v-bind:img-variable":null,"img":"https://ucarecdn.com/4bd770bf-0af1-4a3b-b0e9-4b147e33b442/","class":""},"content":[],"id":"0702063f1","location":"4,1,0,3,1,0,0,6,0"}],"id":"coco","location":"4,1,0,3,1,0,0,6"},{"name":"div","active":true,"minimize":false,"binds":{},"attr":{"class":" is-overlapping-item absolute w-[30%] h-[7%] left-[19%] top-[27%]"},"content":[{"name":"layout-img","active":true,"minimize":false,"binds":{},"attr":{"v-bind:img-variable":null,"img":"https://ucarecdn.com/a4441cc5-f541-4f36-91b4-1ed01abcac02/","class":""},"content":[],"id":"02a6a734d","location":"4,1,0,3,1,0,0,7,0"}],"id":"choco","location":"4,1,0,3,1,0,0,7"},{"name":"div","active":true,"minimize":false,"binds":{},"attr":{"class":" is-overlapping-item absolute w-[30%] h-[4%] left-[16%] top-[26%]"},"content":[{"name":"layout-img","active":true,"minimize":false,"binds":{},"attr":{"v-bind:img-variable":null,"img":"https://ucarecdn.com/962b0f43-913f-445c-872d-5f5b5703ed02/","class":""},"content":[],"id":"081a631d9","location":"4,1,0,3,1,0,0,8,0"}],"id":"colores","location":"4,1,0,3,1,0,0,8"}],"id":"🟪🟩","location":"4,1,0,3,1,0,0"}],"id":"0554e4dbf","location":"4,1,0,3,1,0"}],"id":"✅","location":"4,1,0,3,1"}],"id":"🟦","location":"4,1,0,3"}],"id":"002366884","location":"4,1,0"},{"name":"action-timeline","odatype":"avanzadas","active":true,"minimize":false,"binds":{},"attr":{"show":"5","hide":"","completed":"","completed-audio":"","ok":"","ok-audio":"","error":"","error-audio":""},"content":[{"name":"av-button","odatype":"avanzadas","active":true,"minimize":false,"binds":{},"attr":{"v-bind:nextscene":true,"v-bind:nexttimeline":false,"v-bind:emit-completed":false,"v-bind:emit-ok":false,"v-bind:emit-error":false,"class":""},"content":"Finalizar","id":"0a4914fdd","location":"4,1,1,0"}],"id":"4347986a7","location":"4,1,1"}],"id":"Actividad","location":"4,1"}],"id":"4","location":"4"},{"name":"av-scene","odatype":"avanzadas","active":true,"minimize":false,"binds":{},"attr":{"v-bind:automatic-scene":true,"class":"","end-audio":"","v-bind:force-oks":0},"content":[{"name":"av-end","odatype":"avanzadas","active":true,"minimize":false,"binds":{},"attr":{},"content":[],"id":"046706769","location":"5,0"}],"id":"Fin","location":"5"}],"view":false,"version":"0.9","loaderVersion":"v1.2.12","loader":"https://cdn.jsdelivr.net/gh/bluemx/blueodasv2@v1.2.12/lib/loader.min.js","mediafiles":[{"name":"2.png","uuid":"574d8e1c-de9a-4f06-8b2b-3599639d9ced","cdn":"https://ucarecdn.com/574d8e1c-de9a-4f06-8b2b-3599639d9ced/","isImage":true,"mimeType":"image/png"},{"name":"3.png","uuid":"4ad01cd1-905e-4916-b70a-3318b8af19d7","cdn":"https://ucarecdn.com/4ad01cd1-905e-4916-b70a-3318b8af19d7/","isImage":true,"mimeType":"image/png"},{"name":"4.png","uuid":"4bd770bf-0af1-4a3b-b0e9-4b147e33b442","cdn":"https://ucarecdn.com/4bd770bf-0af1-4a3b-b0e9-4b147e33b442/","isImage":true,"mimeType":"image/png"},{"name":"5.png","uuid":"0afd09ab-99a4-4193-85eb-0a185e12d757","cdn":"https://ucarecdn.com/0afd09ab-99a4-4193-85eb-0a185e12d757/","isImage":true,"mimeType":"image/png"},{"name":"7.png","uuid":"12003898-df80-4d3b-b11f-9f7a1de97619","cdn":"https://ucarecdn.com/12003898-df80-4d3b-b11f-9f7a1de97619/","isImage":true,"mimeType":"image/png"},{"name":"10.png","uuid":"f1df4b48-aaba-457d-9979-42f99580efd5","cdn":"https://ucarecdn.com/f1df4b48-aaba-457d-9979-42f99580efd5/","isImage":true,"mimeType":"image/png"},{"name":"8.png","uuid":"9b30593d-2c28-4726-a6a2-5435492f4f94","cdn":"https://ucarecdn.com/9b30593d-2c28-4726-a6a2-5435492f4f94/","isImage":true,"mimeType":"image/png"},{"name":"9.png","uuid":"962b0f43-913f-445c-872d-5f5b5703ed02","cdn":"https://ucarecdn.com/962b0f43-913f-445c-872d-5f5b5703ed02/","isImage":true,"mimeType":"image/png"},{"name":"6.png","uuid":"346bb254-cad9-49e2-bf2a-34c732eaa65f","cdn":"https://ucarecdn.com/346bb254-cad9-49e2-bf2a-34c732eaa65f/","isImage":true,"mimeType":"image/png"},{"name":"11.png","uuid":"a4441cc5-f541-4f36-91b4-1ed01abcac02","cdn":"https://ucarecdn.com/a4441cc5-f541-4f36-91b4-1ed01abcac02/","isImage":true,"mimeType":"image/png"},{"name":"12.png","uuid":"a9dbbfb0-3b63-4814-b93c-5f5840f79282","cdn":"https://ucarecdn.com/a9dbbfb0-3b63-4814-b93c-5f5840f79282/","isImage":true,"mimeType":"image/png"},{"name":"13.png","uuid":"2c532a91-9ba1-49c1-a584-e61ba247acd6","cdn":"https://ucarecdn.com/2c532a91-9ba1-49c1-a584-e61ba247acd6/","isImage":true,"mimeType":"image/png"},{"name":"17.png","uuid":"6dd5871d-1bb4-49a8-94be-fd8fc117321f","cdn":"https://ucarecdn.com/6dd5871d-1bb4-49a8-94be-fd8fc117321f/","isImage":true,"mimeType":"image/png"},{"name":"18.png","uuid":"8159d052-3b2a-4799-978e-1daf10d3313c","cdn":"https://ucarecdn.com/8159d052-3b2a-4799-978e-1daf10d3313c/","isImage":true,"mimeType":"image/png"},{"name":"20.png","uuid":"3f83f7b5-6b4a-4598-9e8f-2a9c4bcf53d5","cdn":"https://ucarecdn.com/3f83f7b5-6b4a-4598-9e8f-2a9c4bcf53d5/","isImage":true,"mimeType":"image/png"},{"name":"21.png","uuid":"07e04eb7-483d-4622-a60a-41d7fad6871e","cdn":"https://ucarecdn.com/07e04eb7-483d-4622-a60a-41d7fad6871e/","isImage":true,"mimeType":"image/png"},{"name":"22.png","uuid":"ac9a5e9e-9d0d-4916-b265-6d55661ebab9","cdn":"https://ucarecdn.com/ac9a5e9e-9d0d-4916-b265-6d55661ebab9/","isImage":true,"mimeType":"image/png"},{"name":"19.png","uuid":"8bfda199-3baf-4d65-9dd7-f60e4ce24cd8","cdn":"https://ucarecdn.com/8bfda199-3baf-4d65-9dd7-f60e4ce24cd8/","isImage":true,"mimeType":"image/png"},{"name":"15.png","uuid":"51454dea-9d56-4d1e-8678-a127447207fe","cdn":"https://ucarecdn.com/51454dea-9d56-4d1e-8678-a127447207fe/","isImage":true,"mimeType":"image/png"},{"name":"14.png","uuid":"2f511ba3-5bfd-46b6-9713-87a1bdbb5cca","cdn":"https://ucarecdn.com/2f511ba3-5bfd-46b6-9713-87a1bdbb5cca/","isImage":true,"mimeType":"image/png"},{"name":"16.png","uuid":"c4ae2d76-365c-4ebd-ac28-131fa67e8999","cdn":"https://ucarecdn.com/c4ae2d76-365c-4ebd-ac28-131fa67e8999/","isImage":true,"mimeType":"image/png"},{"name":"23.png","uuid":"03e49b8b-df1f-4574-ab7b-44a2e74a28ce","cdn":"https://ucarecdn.com/03e49b8b-df1f-4574-ab7b-44a2e74a28ce/","isImage":true,"mimeType":"image/png"},{"name":"intro.mp3","uuid":"26eaf9e6-9f55-405a-87db-25e926a5a33b","cdn":"https://ucarecdn.com/26eaf9e6-9f55-405a-87db-25e926a5a33b/","isImage":false,"mimeType":"audio/mpeg"},{"name":"v2-que-necesitamos.mp3","uuid":"4ab82894-fb0d-4278-bcc2-f67c558b3537","cdn":"https://ucarecdn.com/4ab82894-fb0d-4278-bcc2-f67c558b3537/","isImage":false,"mimeType":"audio/mpeg"},{"name":"ingredientes.mp3","uuid":"115f8f69-70c8-4975-bcce-31186a32839d","cdn":"https://ucarecdn.com/115f8f69-70c8-4975-bcce-31186a32839d/","isImage":false,"mimeType":"audio/mpeg"},{"name":"v2-Ingredientes-solo.mp3","uuid":"66cb4c28-df08-4908-be58-71d1e5465149","cdn":"https://ucarecdn.com/66cb4c28-df08-4908-be58-71d1e5465149/","isImage":false,"mimeType":"audio/mpeg"},{"name":"24.png","uuid":"3975eefa-c51a-4a0e-9697-5345d265572e","cdn":"https://ucarecdn.com/3975eefa-c51a-4a0e-9697-5345d265572e/","isImage":true,"mimeType":"image/png"},{"name":"1.mp3","uuid":"d2ea3f45-74f8-42d1-95d6-0e9cdc2268ac","cdn":"https://ucarecdn.com/d2ea3f45-74f8-42d1-95d6-0e9cdc2268ac/","isImage":false,"mimeType":"audio/mpeg"},{"name":"como.mp3","uuid":"fe869d21-3989-4c09-856d-0d433369928f","cdn":"https://ucarecdn.com/fe869d21-3989-4c09-856d-0d433369928f/","isImage":false,"mimeType":"audio/mpeg"},{"name":"2.mp3","uuid":"5a19725f-c71a-4d65-8538-6582a4605265","cdn":"https://ucarecdn.com/5a19725f-c71a-4d65-8538-6582a4605265/","isImage":false,"mimeType":"audio/mpeg"},{"name":"3.mp3","uuid":"6173ad2d-ad07-4b84-b8f6-a78f56b7b1b0","cdn":"https://ucarecdn.com/6173ad2d-ad07-4b84-b8f6-a78f56b7b1b0/","isImage":false,"mimeType":"audio/mpeg"},{"name":"4.mp3","uuid":"0eaedeef-c565-47a5-a1c7-1571f4f42f1e","cdn":"https://ucarecdn.com/0eaedeef-c565-47a5-a1c7-1571f4f42f1e/","isImage":false,"mimeType":"audio/mpeg"},{"name":"5.mp3","uuid":"957d3513-6749-4e22-ac46-931dad807874","cdn":"https://ucarecdn.com/957d3513-6749-4e22-ac46-931dad807874/","isImage":false,"mimeType":"audio/mpeg"},{"name":"6.mp3","uuid":"11974619-d82d-4891-a235-3451d5cabdc0","cdn":"https://ucarecdn.com/11974619-d82d-4891-a235-3451d5cabdc0/","isImage":false,"mimeType":"audio/mpeg"},{"name":"7.mp3","uuid":"57a69eb8-9428-4697-9888-fb326a5a0bfb","cdn":"https://ucarecdn.com/57a69eb8-9428-4697-9888-fb326a5a0bfb/","isImage":false,"mimeType":"audio/mpeg"}]}